README.md
setup.py
aps/__init__.py
aps/aps.py
aps.egg-info/PKG-INFO
aps.egg-info/SOURCES.txt
aps.egg-info/dependency_links.txt
aps.egg-info/not-zip-safe
aps.egg-info/top_level.txt