Metadata-Version: 1.0
Name: aps
Version: 0.0.0
Summary: APS Journals API in Python for Humans.
Home-page: http://github.com/ishxiao/aps
Author: Xiao Shang
Author-email: me@ishxiao.com
License: MIT
Platform: UNKNOWN
